am4/libduckdb.dylib
am4/utils.cpython-39-darwin.so
am4/utils/route.pyi
am4/utils/airport.pyi
am4/utils/__init__.pyi
am4/utils/demand.pyi
am4/utils/aircraft.pyi
am4/utils/log.pyi
am4/utils/game.pyi
am4/utils/ticket.pyi
am4/utils/db/__init__.pyi
am4/utils/db/utils.pyi
am4-0.1.8a1.dist-info/RECORD
am4-0.1.8a1.dist-info/WHEEL
am4-0.1.8a1.dist-info/entry_points.txt
am4-0.1.8a1.dist-info/METADATA
am4-0.1.8a1.dist-info/licenses/LICENSE
