Metadata-Version: 2.1
Name: am4
Version: 0.1.8a1
Summary: Tools and utilities for the game Airline Manager 4.
Author-Email: cathaypacific8747 <abraham@ylcheung.com>
License: MIT License
Classifier: Development Status :: 4 - Beta
Classifier: License :: OSI Approved :: MIT License
Classifier: Programming Language :: Python :: 3 :: Only
Classifier: Programming Language :: Python :: 3.11
Classifier: Programming Language :: Python :: 3.10
Classifier: Programming Language :: Python :: 3.9
Requires-Python: >=3.9
Requires-Dist: rich>=13.7.0
Requires-Dist: httpx>=0.26.0
Requires-Dist: pydantic>=2.6.1
Requires-Dist: loguru>=0.7.2
Requires-Dist: typer>=0.9.0
Requires-Dist: orjson>=3.9.13
Requires-Dist: pybind11>=2.11.1; extra == "dev"
Requires-Dist: pybind11-stubgen>=2.4.2; extra == "dev"
Requires-Dist: pytest>=7.4.4; extra == "dev"
Requires-Dist: pytest-asyncio>=0.23.4; extra == "dev"
Requires-Dist: ruff; extra == "dev"
Requires-Dist: fastapi>=0.109.2; extra == "api"
Requires-Dist: uvicorn>=0.27.0; extra == "api"
Requires-Dist: matplotlib>=3.7.1; extra == "bot"
Requires-Dist: Pillow>=9.5.0; extra == "bot"
Requires-Dist: discord.py>=2.2.3; extra == "bot"
Requires-Dist: pyproj>=3.6.1; extra == "bot"
Requires-Dist: cmocean>=3.1.3; extra == "bot"
Requires-Dist: pyarrow>=15.0.0; extra == "bot"
Requires-Dist: beautifulsoup4; extra == "debug"
Requires-Dist: pyjsparser; extra == "debug"
Requires-Dist: pandas; extra == "debug"
Requires-Dist: seaborn; extra == "debug"
Requires-Dist: statsmodels; extra == "debug"
Requires-Dist: PyQt6; extra == "debug"
Requires-Dist: tqdm; extra == "debug"
Requires-Dist: ipykernel; extra == "debug"
Requires-Dist: urllib3; extra == "debug"
Provides-Extra: dev
Provides-Extra: api
Provides-Extra: bot
Provides-Extra: debug
License-File: LICENSE
